[
{"id":"vp3_accountfor","term":"account for","meaning":"explain or be the reason for","example":"How do you account for the loss?<br>This accounts for the delay.<br>He couldn't account for the money.","type":"phrasal","tier":3},
{"id":"vp3_backup","term":"back up","meaning":"support; or make a copy of data","example":"Back up your files.<br>I'll back you up.<br>Can someone back up this claim?","type":"phrasal","tier":2},
{"id":"vp3_blowup","term":"blow up","meaning":"explode; or suddenly get angry","example":"He blew up over a small thing.<br>The balloon blew up.<br>Don't blow up at me.","type":"phrasal","tier":2},
{"id":"vp3_bringabout","term":"bring about","meaning":"cause something to happen","example":"The reform brought about change.<br>What brought this about?<br>Technology brought about progress.","type":"phrasal","tier":3},
{"id":"vp3_callon","term":"call on","meaning":"ask someone to do something; or visit","example":"They called on him to resign.<br>I'll call on you tomorrow.<br>She was called on to speak.","type":"phrasal","tier":3},
{"id":"vp3_carryout","term":"carry out","meaning":"perform or complete a task","example":"They carried out the tests.<br>Carry out the plan.<br>The work was carried out safely.","type":"phrasal","tier":2},
{"id":"vp3_catchup","term":"catch up","meaning":"reach the same level as others","example":"I need to catch up on reading.<br>Let's catch up soon.<br>He caught up with the group.","type":"phrasal","tier":2},
{"id":"vp3_comeupwith","term":"come up with","meaning":"think of an idea or plan","example":"We came up with a solution.<br>She came up with the name.<br>Can you come up with ideas?","type":"phrasal","tier":2},
{"id":"vp3_counton","term":"count on","meaning":"rely on","example":"You can count on me.<br>Don't count on it.<br>We count on your support.","type":"phrasal","tier":2},
{"id":"vp3_drawup","term":"draw up","meaning":"prepare a document or plan","example":"They drew up a contract.<br>Draw up a list.<br>We drew up a budget.","type":"phrasal","tier":3},
{"id":"vp3_dropoff","term":"drop off","meaning":"take someone somewhere; or fall asleep","example":"I'll drop you off.<br>He dropped off during the film.<br>Sales dropped off.","type":"phrasal","tier":2},
{"id":"vp3_getby","term":"get by","meaning":"manage with what you have","example":"We get by on a small income.<br>I can get by in French.<br>They just get by.","type":"phrasal","tier":3},
{"id":"vp3_getridof","term":"get rid of","meaning":"remove or throw away","example":"Let's get rid of the old sofa.<br>Get rid of the clutter.<br>I can't get rid of this cough.","type":"phrasal","tier":2},
{"id":"vp3_giveaway","term":"give away","meaning":"give for free; or reveal a secret","example":"They gave away free samples.<br>Don't give away the ending.<br>She gave away her old clothes.","type":"phrasal","tier":2},
{"id":"vp3_handin","term":"hand in","meaning":"submit something","example":"Hand in your work by Friday.<br>He handed in his notice.<br>Please hand it in.","type":"phrasal","tier":2},
{"id":"vp3_holdback","term":"hold back","meaning":"stop yourself; or keep something secret","example":"Don't hold back.<br>She held back her tears.<br>He's holding back information.","type":"phrasal","tier":3},
{"id":"vp3_lookinto","term":"look into","meaning":"investigate","example":"We'll look into the problem.<br>Let me look into it.<br>Police are looking into the case.","type":"phrasal","tier":2},
{"id":"vp3_makeout","term":"make out","meaning":"see or hear with difficulty; or understand","example":"I couldn't make out the sign.<br>Can you make out the words?<br>I can't make out his writing.","type":"phrasal","tier":3},
{"id":"vp3_passaway","term":"pass away","meaning":"die (polite)","example":"Her grandfather passed away.<br>He passed away peacefully.<br>They lost a friend who passed away.","type":"phrasal","tier":3},
{"id":"vp3_putforward","term":"put forward","meaning":"suggest a plan or idea","example":"She put forward a proposal.<br>He put his name forward.<br>They put forward a new idea.","type":"phrasal","tier":3},
{"id":"vp3_ruleout","term":"rule out","meaning":"decide something is not possible","example":"We can't rule out rain.<br>Don't rule it out.<br>Police ruled out foul play.","type":"phrasal","tier":3},
{"id":"vp3_setaside","term":"set aside","meaning":"save for later; or ignore for now","example":"Set aside some money.<br>Let's set aside our differences.<br>She set aside time to study.","type":"phrasal","tier":3},
{"id":"vp3_standout","term":"stand out","meaning":"be easily noticed","example":"Her work stands out.<br>He stands out in a crowd.<br>One detail stood out.","type":"phrasal","tier":2},
{"id":"vp3_takeafter","term":"take after","meaning":"resemble a family member","example":"She takes after her mother.<br>He takes after his dad.<br>Who do you take after?","type":"phrasal","tier":3},
{"id":"vp3_takein","term":"take in","meaning":"understand and remember; or deceive","example":"It's a lot to take in.<br>I couldn't take it all in.<br>Don't be taken in by him.","type":"phrasal","tier":3},
{"id":"vp3_turndown","term":"turn down","meaning":"refuse; or lower the volume","example":"He turned down the offer.<br>Turn down the music.<br>They turned my request down.","type":"phrasal","tier":2},
{"id":"vp3_turninto","term":"turn into","meaning":"become something different","example":"The rain turned into snow.<br>It turned into a great day.<br>The caterpillar turned into a butterfly.","type":"phrasal","tier":2},
{"id":"vp3_watchout","term":"watch out","meaning":"be careful","example":"Watch out for the step.<br>Watch out, it's hot!<br>Watch out for scams.","type":"phrasal","tier":2},
{"id":"vp3_wearout","term":"wear out","meaning":"become unusable from use; or exhaust","example":"My shoes wore out.<br>The kids wore me out.<br>The batteries wore out.","type":"phrasal","tier":3},
{"id":"vp3_breakup2","term":"set up (arrange)","meaning":"organize or establish something","example":"They set up a charity.<br>We set up the equipment.<br>She set up her own business.","type":"phrasal","tier":2},
{"id":"vp3_runinto2","term":"come down with","meaning":"start to have an illness","example":"I'm coming down with a cold.<br>She came down with the flu.<br>He came down with a fever.","type":"phrasal","tier":3}
]
