[
{"id":"vw3_become","term":"become","meaning":"start to be something","example":"She became a doctor.<br>It became cold at night.<br>They became good friends.","type":"word","tier":1},
{"id":"vw3_include","term":"include","meaning":"have as a part","example":"The price includes breakfast.<br>Does it include tax?<br>The team includes ten people.","type":"word","tier":1},
{"id":"vw3_follow","term":"follow","meaning":"go after; or do as told","example":"Follow me, please.<br>Follow the instructions.<br>A dog followed us home.","type":"word","tier":1},
{"id":"vw3_lead","term":"lead","meaning":"guide or be in front","example":"She leads the team.<br>This road leads to town.<br>He led us inside.","type":"word","tier":1},
{"id":"vw3_bring","term":"bring","meaning":"take something to a place","example":"Bring your books tomorrow.<br>Can I bring a friend?<br>She brought a gift.","type":"word","tier":1},
{"id":"vw3_build","term":"build","meaning":"make by putting parts together","example":"They built a house.<br>Let's build a team.<br>Trust takes time to build.","type":"word","tier":1},
{"id":"vw3_carry","term":"carry","meaning":"hold and move something","example":"Can you carry this bag?<br>She carried the baby.<br>The bus carries many people.","type":"word","tier":1},
{"id":"vw3_catch","term":"catch","meaning":"take hold of something moving","example":"Catch the ball!<br>I caught the train.<br>He caught a cold.","type":"word","tier":1},
{"id":"vw3_cause","term":"cause","meaning":"make something happen","example":"The rain caused delays.<br>What caused the fire?<br>Stress can cause illness.","type":"word","tier":1},
{"id":"vw3_cost","term":"cost","meaning":"have a price of","example":"It costs ten dollars.<br>How much does it cost?<br>That mistake cost us a lot.","type":"word","tier":1},
{"id":"vw3_cover","term":"cover","meaning":"put something over; or include","example":"Cover the pan with a lid.<br>Snow covered the roads.<br>The book covers many topics.","type":"word","tier":1},
{"id":"vw3_cut","term":"cut","meaning":"divide with a knife or scissors","example":"Cut the paper in half.<br>He cut his finger.<br>Let's cut costs.","type":"word","tier":1},
{"id":"vw3_draw","term":"draw","meaning":"make a picture with lines","example":"She drew a map.<br>The child drew a cat.<br>Draw a straight line.","type":"word","tier":1},
{"id":"vw3_fall","term":"fall","meaning":"move down suddenly","example":"Leaves fall in autumn.<br>Be careful not to fall.<br>Prices fell sharply.","type":"word","tier":1},
{"id":"vw3_feel","term":"feel","meaning":"experience an emotion or touch","example":"I feel happy today.<br>It feels soft.<br>How do you feel?","type":"word","tier":1},
{"id":"vw3_grow","term":"grow","meaning":"become bigger or develop","example":"Plants grow in spring.<br>The city is growing fast.<br>Children grow quickly.","type":"word","tier":1},
{"id":"vw3_hold","term":"hold","meaning":"have in your hands","example":"Hold this for a second.<br>She held the door open.<br>Hold on tight.","type":"word","tier":1},
{"id":"vw3_join","term":"join","meaning":"become a member; or connect","example":"I joined the club.<br>Will you join us?<br>Join the two pieces.","type":"word","tier":1},
{"id":"vw3_lose","term":"lose","meaning":"no longer have; or not win","example":"Don't lose your keys.<br>We lost the game.<br>I'm losing patience.","type":"word","tier":1},
{"id":"vw3_mean","term":"mean","meaning":"have as a meaning; or intend","example":"What does this word mean?<br>I didn't mean to upset you.<br>This means a lot to me.","type":"word","tier":1},
{"id":"vw3_move","term":"move","meaning":"change position or place","example":"Please move your car.<br>We moved to a new city.<br>Don't move!","type":"word","tier":1},
{"id":"vw3_pay","term":"pay","meaning":"give money for something","example":"I'll pay for lunch.<br>They pay by card.<br>It pays to be honest.","type":"word","tier":1},
{"id":"vw3_prove","term":"prove","meaning":"show that something is true","example":"Can you prove it?<br>The results prove the theory.<br>He proved them wrong.","type":"word","tier":2},
{"id":"vw3_raise","term":"raise","meaning":"lift up; or increase","example":"Raise your hand.<br>They raised prices.<br>She raised three children.","type":"word","tier":1},
{"id":"vw3_reach","term":"reach","meaning":"arrive at; or stretch to touch","example":"We reached the top.<br>I can't reach the shelf.<br>Reach me by phone.","type":"word","tier":1},
{"id":"vw3_save","term":"save","meaning":"keep for later; or rescue","example":"Save some money each month.<br>He saved the file.<br>She saved his life.","type":"word","tier":1},
{"id":"vw3_seem","term":"seem","meaning":"appear to be","example":"You seem tired.<br>It seems easy.<br>She seems happy.","type":"word","tier":1},
{"id":"vw3_send","term":"send","meaning":"make something go somewhere","example":"I'll send you the file.<br>Send my regards.<br>They sent a letter.","type":"word","tier":1},
{"id":"vw3_serve","term":"serve","meaning":"give food or help to people","example":"They serve breakfast at eight.<br>How can I serve you?<br>This serves four people.","type":"word","tier":2},
{"id":"vw3_share","term":"share","meaning":"have or use with others","example":"Let's share the pizza.<br>Share your ideas.<br>We share an office.","type":"word","tier":1},
{"id":"vw3_show","term":"show","meaning":"let someone see something","example":"Show me your work.<br>I'll show you the way.<br>The data shows growth.","type":"word","tier":1},
{"id":"vw3_sit","term":"sit","meaning":"rest on a seat","example":"Please sit down.<br>We sat by the window.<br>Sit still.","type":"word","tier":1},
{"id":"vw3_stand","term":"stand","meaning":"be on your feet","example":"Stand up, please.<br>I can't stand the noise.<br>She stood near the door.","type":"word","tier":1},
{"id":"vw3_support","term":"support","meaning":"help or agree with","example":"I support your idea.<br>They support the team.<br>The beam supports the roof.","type":"word","tier":2},
{"id":"vw3_win","term":"win","meaning":"be first or best in a contest","example":"Our team won.<br>She won a prize.<br>You can't win every time.","type":"word","tier":1},
{"id":"vw3_worry","term":"worry","meaning":"feel anxious","example":"Don't worry about it.<br>She worries too much.<br>It's nothing to worry about.","type":"word","tier":1},
{"id":"vw3_wonder","term":"wonder","meaning":"want to know; think about","example":"I wonder where she is.<br>I wonder why.<br>It makes you wonder.","type":"word","tier":2},
{"id":"vw3_suppose","term":"suppose","meaning":"think something is probably true","example":"I suppose you're right.<br>Suppose it rains?<br>I'm supposed to be there.","type":"word","tier":2},
{"id":"vw3_recognise","term":"recognise","meaning":"know someone or something from before","example":"I didn't recognise you!<br>She recognised the song.<br>They recognised his talent.","type":"word","tier":2},
{"id":"vw3_remind","term":"remind","meaning":"make someone remember","example":"Remind me to call her.<br>You remind me of my brother.<br>This reminds me of home.","type":"word","tier":2},
{"id":"vw3_possible","term":"possible","meaning":"able to happen or be done","example":"Is it possible to change it?<br>Anything is possible.<br>Come as soon as possible.","type":"word","tier":1},
{"id":"vw3_certain","term":"certain","meaning":"completely sure","example":"I'm certain it's true.<br>Are you certain?<br>One thing is certain.","type":"word","tier":2},
{"id":"vw3_similar","term":"similar","meaning":"almost the same","example":"Our ideas are similar.<br>They look similar.<br>It's similar to mine.","type":"word","tier":1},
{"id":"vw3_common","term":"common","meaning":"happening often; shared by many","example":"It's a common mistake.<br>We have a lot in common.<br>It's common knowledge.","type":"word","tier":1},
{"id":"vw3_recent","term":"recent","meaning":"happening a short time ago","example":"In recent years, things changed.<br>a recent photo<br>recent news","type":"word","tier":2},
{"id":"vw3_serious","term":"serious","meaning":"important and not joking; severe","example":"This is a serious problem.<br>Are you serious?<br>a serious illness","type":"word","tier":1},
{"id":"vw3_particular","term":"particular","meaning":"specific; this one and not others","example":"Is there a particular one you like?<br>in this particular case<br>She's very particular about food.","type":"word","tier":2},
{"id":"vw3_various","term":"various","meaning":"several different","example":"We sell various sizes.<br>for various reasons<br>various colours","type":"word","tier":2},
{"id":"vw3_several","term":"several","meaning":"more than two but not many","example":"I called several times.<br>several people<br>several days ago","type":"word","tier":1},
{"id":"vw3_whole","term":"whole","meaning":"complete; all of something","example":"I read the whole book.<br>the whole day<br>the whole world","type":"word","tier":1},
{"id":"vw3_main","term":"main","meaning":"most important","example":"What's the main reason?<br>the main road<br>the main point","type":"word","tier":1},
{"id":"vw3_real","term":"real","meaning":"true; not fake","example":"Is this a real diamond?<br>the real reason<br>in real life","type":"word","tier":1},
{"id":"vw3_sure","term":"sure","meaning":"certain; confident","example":"Are you sure?<br>I'm not sure.<br>Sure, no problem.","type":"word","tier":1},
{"id":"vw3_true","term":"true","meaning":"correct; based on fact","example":"That's true.<br>Is it true?<br>a true story","type":"word","tier":1},
{"id":"vw3_ready","term":"ready","meaning":"prepared","example":"Are you ready to go?<br>Dinner is ready.<br>I'm ready when you are.","type":"word","tier":1},
{"id":"vw3_safe","term":"safe","meaning":"not in danger","example":"Drive safe.<br>Keep it in a safe place.<br>You're safe now.","type":"word","tier":1},
{"id":"vw3_clear","term":"clear","meaning":"easy to understand or see","example":"The instructions are clear.<br>a clear sky<br>Is that clear?","type":"word","tier":1},
{"id":"vw3_simple","term":"simple","meaning":"easy; not complicated","example":"It's a simple recipe.<br>a simple question<br>Keep it simple.","type":"word","tier":1},
{"id":"vw3_modern","term":"modern","meaning":"of the present time","example":"a modern building<br>modern technology<br>in modern times","type":"word","tier":1},
{"id":"vw3_useful","term":"useful","meaning":"helpful for a purpose","example":"This app is very useful.<br>useful advice<br>a useful tool","type":"word","tier":1}
]
